dagster_dify/__init__.py
dagster_dify/py.typed
dagster_dify/resources.py
dagster_dify/version.py
dagster_dify-0.27.15.1.dist-info/METADATA
dagster_dify-0.27.15.1.dist-info/WHEEL
dagster_dify-0.27.15.1.dist-info/RECORD
