Metadata-Version: 2.4
Name: dagster-dify
Version: 0.27.15.1
Summary: A dagster plugin for the Dify
Author-email: YiZixuan <sqkkyzx@qq.com>
Requires-Python: >=3.12
Requires-Dist: dagster>1.11.0
Requires-Dist: httpx
Requires-Dist: pydantic
